{
    "asset": {
        "format": "jpg",
        "id": "198f43f5727015e5c56f3f2330554091",
        "name": "pomeranian_171.jpg",
        "path": "file:C:/Users/Fuzail/Desktop/internship/TrainYourOwnYOLO/Data/Source_Images/Training_Images/pomeranian_171.jpg",
        "size": {
            "width": 225,
            "height": 300
        },
        "state": 2,
        "type": 1
    },
    "regions": [
        {
            "id": "Y3FY-du5h",
            "type": "RECTANGLE",
            "tags": [
                "Normal"
            ],
            "boundingBox": {
                "height": 58.33333333333333,
                "width": 62.745098039215684,
                "left": 44.11764705882353,
                "top": 78.92156862745098
            },
            "points": [
                {
                    "x": 44.11764705882353,
                    "y": 78.92156862745098
                },
                {
                    "x": 106.86274509803921,
                    "y": 78.92156862745098
                },
                {
                    "x": 106.86274509803921,
                    "y": 137.2549019607843
                },
                {
                    "x": 44.11764705882353,
                    "y": 137.2549019607843
                }
            ]
        },
        {
            "id": "VxXKphmTi",
            "type": "RECTANGLE",
            "tags": [
                "Normal"
            ],
            "boundingBox": {
                "height": 81.37254901960785,
                "width": 93.13725490196079,
                "left": 40.19607843137255,
                "top": 71.07843137254902
            },
            "points": [
                {
                    "x": 40.19607843137255,
                    "y": 71.07843137254902
                },
                {
                    "x": 133.33333333333331,
                    "y": 71.07843137254902
                },
                {
                    "x": 133.33333333333331,
                    "y": 152.45098039215685
                },
                {
                    "x": 40.19607843137255,
                    "y": 152.45098039215685
                }
            ]
        }
    ],
    "version": "2.1.0"
}