{
    "asset": {
        "format": "jpg",
        "id": "652d119c0c7a69fef19b963db5a1b031",
        "name": "n02112018_13636.jpg",
        "path": "file:C:/Users/Fuzail/Desktop/internship/TrainYourOwnYOLO/Data/Source_Images/Training_Images/n02112018_13636.jpg",
        "size": {
            "width": 500,
            "height": 375
        },
        "state": 2,
        "type": 1
    },
    "regions": [
        {
            "id": "nw5sYJLWB",
            "type": "RECTANGLE",
            "tags": [
                "Sad"
            ],
            "boundingBox": {
                "height": 169.11764705882354,
                "width": 175.2450980392157,
                "left": 187.19362745098042,
                "top": 166.05392156862746
            },
            "points": [
                {
                    "x": 187.19362745098042,
                    "y": 166.05392156862746
                },
                {
                    "x": 362.4387254901961,
                    "y": 166.05392156862746
                },
                {
                    "x": 362.4387254901961,
                    "y": 335.171568627451
                },
                {
                    "x": 187.19362745098042,
                    "y": 335.171568627451
                }
            ]
        },
        {
            "id": "3s4ZGOz-f",
            "type": "RECTANGLE",
            "tags": [
                "Sad"
            ],
            "boundingBox": {
                "height": 277.57352941176475,
                "width": 265.9313725490196,
                "left": 149.20343137254903,
                "top": 72.91666666666667
            },
            "points": [
                {
                    "x": 149.20343137254903,
                    "y": 72.91666666666667
                },
                {
                    "x": 415.1348039215687,
                    "y": 72.91666666666667
                },
                {
                    "x": 415.1348039215687,
                    "y": 350.4901960784314
                },
                {
                    "x": 149.20343137254903,
                    "y": 350.4901960784314
                }
            ]
        }
    ],
    "version": "2.1.0"
}