{
    "asset": {
        "format": "jpg",
        "id": "db043adde994a7e2c095faf12e8a0521",
        "name": "pomeranian_61.jpg",
        "path": "file:C:/Users/Fuzail/Desktop/internship/TrainYourOwnYOLO/Data/Source_Images/Training_Images/pomeranian_61.jpg",
        "size": {
            "width": 500,
            "height": 375
        },
        "state": 2,
        "type": 1
    },
    "regions": [
        {
            "id": "F6-7bzQ6b",
            "type": "RECTANGLE",
            "tags": [
                "Normal"
            ],
            "boundingBox": {
                "height": 118.87254901960785,
                "width": 148.89705882352942,
                "left": 160.23284313725492,
                "top": 129.28921568627453
            },
            "points": [
                {
                    "x": 160.23284313725492,
                    "y": 129.28921568627453
                },
                {
                    "x": 309.1299019607843,
                    "y": 129.28921568627453
                },
                {
                    "x": 309.1299019607843,
                    "y": 248.16176470588238
                },
                {
                    "x": 160.23284313725492,
                    "y": 248.16176470588238
                }
            ]
        },
        {
            "id": "8zBGkNSLc",
            "type": "RECTANGLE",
            "tags": [
                "Normal"
            ],
            "boundingBox": {
                "height": 158.70098039215688,
                "width": 188.72549019607845,
                "left": 144.91421568627453,
                "top": 112.74509803921569
            },
            "points": [
                {
                    "x": 144.91421568627453,
                    "y": 112.74509803921569
                },
                {
                    "x": 333.639705882353,
                    "y": 112.74509803921569
                },
                {
                    "x": 333.639705882353,
                    "y": 271.44607843137254
                },
                {
                    "x": 144.91421568627453,
                    "y": 271.44607843137254
                }
            ]
        }
    ],
    "version": "2.1.0"
}