{
    "asset": {
        "format": "jpg",
        "id": "f1dc8f47e57ffcaba72be9273c046799",
        "name": "pomeranian_51.jpg",
        "path": "file:C:/Users/Fuzail/Desktop/internship/TrainYourOwnYOLO/Data/Source_Images/Training_Images/pomeranian_51.jpg",
        "size": {
            "width": 500,
            "height": 375
        },
        "state": 2,
        "type": 1
    },
    "regions": [
        {
            "id": "3xA5XHIOq",
            "type": "RECTANGLE",
            "tags": [
                "Normal"
            ],
            "boundingBox": {
                "height": 52.696078431372555,
                "width": 53.92156862745098,
                "left": 192.70833333333334,
                "top": 106.61764705882354
            },
            "points": [
                {
                    "x": 192.70833333333334,
                    "y": 106.61764705882354
                },
                {
                    "x": 246.62990196078434,
                    "y": 106.61764705882354
                },
                {
                    "x": 246.62990196078434,
                    "y": 159.31372549019608
                },
                {
                    "x": 192.70833333333334,
                    "y": 159.31372549019608
                }
            ]
        },
        {
            "id": "73MudTJhT",
            "type": "RECTANGLE",
            "tags": [
                "Normal"
            ],
            "boundingBox": {
                "height": 97.4264705882353,
                "width": 79.65686274509804,
                "left": 184.74264705882354,
                "top": 94.36274509803923
            },
            "points": [
                {
                    "x": 184.74264705882354,
                    "y": 94.36274509803923
                },
                {
                    "x": 264.3995098039216,
                    "y": 94.36274509803923
                },
                {
                    "x": 264.3995098039216,
                    "y": 191.78921568627453
                },
                {
                    "x": 184.74264705882354,
                    "y": 191.78921568627453
                }
            ]
        }
    ],
    "version": "2.1.0"
}